eurec4a/__init__.py
eurec4a/_version.py
eurec4a-0.0.6.dist-info/METADATA
eurec4a-0.0.6.dist-info/WHEEL
eurec4a-0.0.6.dist-info/top_level.txt
eurec4a-0.0.6.dist-info/RECORD
