Metadata-Version: 2.1
Name: eurec4a
Version: 0.0.6
Summary: common utilities for analysing data from the EUREC4A field campaign
Author-email: Tobias Kölling <tobias.koelling@mpimet.mpg.de>
License: MIT
Classifier: Programming Language :: Python :: 3
Classifier: License :: OSI Approved :: MIT License
Classifier: Operating System :: OS Independent
Requires-Python: >=3.8
Requires-Dist: requests
Requires-Dist: pyyaml
Requires-Dist: intake !=0.6.1,<2.0.0
Requires-Dist: aiohttp
Requires-Dist: fsspec >=0.7.4
Requires-Dist: ipfsspec
Provides-Extra: data
Requires-Dist: xarray ; extra == 'data'
Requires-Dist: zarr ; extra == 'data'
Requires-Dist: netcdf4 !=1.5.4,!=1.5.5,!=1.5.5.1,!=1.6.0,!=1.6.1,!=1.6.2,!=1.6.3,!=1.6.4 ; extra == 'data'
Requires-Dist: s3fs ; extra == 'data'
Requires-Dist: requests ; extra == 'data'
Requires-Dist: intake-xarray >=0.3.2 ; extra == 'data'
